mcp_file_contents_reader/__init__.py
mcp_file_contents_reader/file_handlers.py
mcp_file_contents_reader/server.py
mcp_file_contents_reader-1.0.20.dist-info/METADATA
mcp_file_contents_reader-1.0.20.dist-info/WHEEL
mcp_file_contents_reader-1.0.20.dist-info/entry_points.txt
mcp_file_contents_reader-1.0.20.dist-info/top_level.txt
mcp_file_contents_reader-1.0.20.dist-info/RECORD
