Metadata-Version: 2.4
Name: mcp-file-contents-reader
Version: 1.0.20
Summary: MCP (Model Context Protocol) server for reading and analyzing various file formats including PDF, Excel, Word, and PowerPoint
Author-email: MCP File Reader Team <contact@example.com>
License-Expression: MIT
Project-URL: Homepage, https://github.com/choipureum/mcp-file-contents-reader
Project-URL: Repository, https://github.com/choipureum/mcp-file-contents-reader
Project-URL: Issues, https://github.com/choipureum/mcp-file-contents-reader/issues
Classifier: Development Status :: 4 - Beta
Classifier: Intended Audience :: Developers
Classifier: Programming Language :: Python :: 3
Classifier: Programming Language :: Python :: 3.8
Classifier: Programming Language :: Python :: 3.9
Classifier: Programming Language :: Python :: 3.10
Classifier: Programming Language :: Python :: 3.11
Classifier: Programming Language :: Python :: 3.12
Classifier: Programming Language :: Python :: 3.13
Requires-Python: >=3.8
Requires-Dist: fastmcp>=0.1.0
Requires-Dist: pandas>=2.0.0
Requires-Dist: openpyxl>=3.1.0
Requires-Dist: pypdf>=4.0.0
Requires-Dist: python-pptx>=0.6.21
Requires-Dist: python-docx>=0.8.11
Requires-Dist: aiofiles>=23.0.0
Requires-Dist: pydantic>=2.0.0
Requires-Dist: reportlab>=4.0.0
Provides-Extra: dev
Requires-Dist: pytest>=7.0.0; extra == "dev"
Requires-Dist: pytest-asyncio>=0.21.0; extra == "dev"
Requires-Dist: black>=23.0.0; extra == "dev"
Requires-Dist: flake8>=6.0.0; extra == "dev"
Requires-Dist: mypy>=1.0.0; extra == "dev"
